FractalTree/__init__.py
Tree/Core.py
Tree/Draw.py
Tree/__init__.py
Tree/cli.py
Tree/core.py
Tree/draw.py
Tree/utils.py
Tree-0.2.3.dist-info/DESCRIPTION.rst
Tree-0.2.3.dist-info/METADATA
Tree-0.2.3.dist-info/RECORD
Tree-0.2.3.dist-info/WHEEL
Tree-0.2.3.dist-info/entry_points.txt
Tree-0.2.3.dist-info/metadata.json
Tree-0.2.3.dist-info/top_level.txt
