Metadata-Version: 2.0
Name: Tree
Version: 0.2.3
Summary: A package for creating and drawing trees
Home-page: https://github.com/PixelwarStudio/PyTree
Author: Pixelwar
Author-email: UNKNOWN
License: MIT
Platform: UNKNOWN
Classifier: Development Status :: 4 - Beta
Classifier: Intended Audience :: Developers
Classifier: License :: OSI Approved :: MIT License
Classifier: Programming Language :: Python :: 3.5
Classifier: Topic :: Scientific/Engineering :: Mathematics
Requires-Dist: Pillow
Requires-Dist: click
Requires-Dist: setuptools
Requires-Dist: svgwrite
